pypette/__init__.py
pypette/__version__.py
pypette/jobs.py
pypette/pipes.py
pypette/threadwrapper.py
pypette-0.0.12.dist-info/LICENSE
pypette-0.0.12.dist-info/WHEEL
pypette-0.0.12.dist-info/METADATA
pypette-0.0.12.dist-info/RECORD
