Metadata-Version: 2.1
Name: pypette
Version: 0.0.12
Summary: pypette (to be read as pipette) is a module which makes building pipelines ridiculously simple, allowing users to control the flow with minimal instructions.
Home-page: https://csurfer.github.io/pypette
License: MIT
Keywords: pipeline,dev-tool,threads,multithreading,python
Author: csurfer
Author-email: sharma.vishwas88@gmail.com
Requires-Python: >=3.6,<4.0
Classifier: Development Status :: 3 - Alpha
Classifier: Intended Audience :: Developers
Classifier: Intended Audience :: Education
Classifier: License :: OSI Approved :: MIT License
Classifier: Operating System :: POSIX
Classifier: Programming Language :: Python :: 3
Classifier: Programming Language :: Python :: 3.6
Classifier: Programming Language :: Python :: 3.7
Classifier: Programming Language :: Python :: 3.8
Classifier: Programming Language :: Python :: 3.9
Classifier: Topic :: Software Development :: Build Tools
Classifier: Topic :: Software Development :: Libraries :: Python Modules
Requires-Dist: Sphinx (>=4.1.2,<5.0.0)
Requires-Dist: crayons (>=0.4.0,<0.5.0)
Requires-Dist: sphinx-autobuild (>=2021.3.14,<2022.0.0)
Project-URL: Repository, https://github.com/csurfer/pypette
